{
  "title": {
    "zh": "中文分类",
    "en": "Category"
  },
  "demos": [
    {
      "filename": "default.js",
      "title": {
        "zh": "对齐线",
        "en": "SnapLine"
      },
      "screenshot": "https://gw.alipayobjects.com/mdn/rms_f8c6a0/afts/img/A*fRMFSZCjuoMAAAAAAAAAAAAAARQnAQ"
    },
    {
      "filename": "custom.js",
      "title": {
        "zh": "自定义对齐线样式",
        "en": "Custom SnapLine"
      },
      "screenshot": "https://gw.alipayobjects.com/mdn/rms_f8c6a0/afts/img/A*G-vPSa3I1lkAAAAAAAAAAAAAARQnAQ"
    }
  ]
}
